seniverse/__init__.py
seniverse/client.py
seniverse/exceptions.py
seniverse/types.py
seniverse_py-0.1.1.dist-info/LICENSE
seniverse_py-0.1.1.dist-info/WHEEL
seniverse_py-0.1.1.dist-info/METADATA
seniverse_py-0.1.1.dist-info/RECORD
