Metadata-Version: 2.1
Name: seniverse-py
Version: 0.1.1
Summary: 心知天气第三方SDK / seniverse third party sdk for python3
License: GPL-v3
Author: weak_ptr
Author-email: weak_ptr@outlook.com
Requires-Python: >=3.6,<4.0
Classifier: License :: Other/Proprietary License
Classifier: Programming Language :: Python :: 3
Classifier: Programming Language :: Python :: 3.6
Classifier: Programming Language :: Python :: 3.7
Classifier: Programming Language :: Python :: 3.8
Classifier: Programming Language :: Python :: 3.9
Requires-Dist: typing-extensions (>=3.7.4,<4.0.0)
